Metadata-Version: 1.0
Name: fig2pen
Version: 0.3.0
Summary: fig2pen
Home-page: UNKNOWN
Author: Nicolas Kruchten
Author-email: UNKNOWN
License: MIT
Platform: UNKNOWN
